Email_Usage/__init__.py
Email_Usage/main.py
Email_Usage-2.1.dist-info/METADATA
Email_Usage-2.1.dist-info/WHEEL
Email_Usage-2.1.dist-info/top_level.txt
Email_Usage-2.1.dist-info/RECORD
