Metadata-Version: 2.1
Name: Email_Usage
Version: 2.1
